mailshot/__init__.py
mailshot/client.py
mailshot/config.py
mailshot/mailshot.py
mailshot/utils.py
mailshot-1.0.0.dist-info/LICENSE
mailshot-1.0.0.dist-info/METADATA
mailshot-1.0.0.dist-info/WHEEL
mailshot-1.0.0.dist-info/top_level.txt
mailshot-1.0.0.dist-info/RECORD
