Metadata-Version: 2.1
Name: mailshot
Version: 1.0.0
Summary: Mailshot is a simple package to send email via Gmail.
Home-page: https://github.com/rohan-pednekar/mailshot
Author: Rohan Pednekar
Author-email: developer.rohan.pednekar@gmail.com
License: UNKNOWN
Project-URL: Bug Tracker, https://github.com/rohan-pednekar/mailshot/issues
Platform: UNKNOWN
Classifier: Programming Language :: Python :: 3
Classifier: License :: OSI Approved :: MIT License
Classifier: Operating System :: OS Independent
Requires-Python: >=3.6
License-File: LICENSE
